MANIFEST.in
README.md
setup.cfg
setup.py
version_module_A.py
module_A.egg-info/PKG-INFO
module_A.egg-info/SOURCES.txt
module_A.egg-info/dependency_links.txt
module_A.egg-info/not-zip-safe
module_A.egg-info/top_level.txt