Metadata-Version: 2.1
Name: module-A
Version: 2.6.0
Summary: Macrolib's description
Home-page: https://github.com/maite828/module_A.git
License: MIT
Download-URL: https://github.com/maite828/modlue_A/archive/refs/heads/main.zip
Platform: UNKNOWN
Requires-Python: >=3.6
